mykitchen/__init__.py
mykitchen/__main__.py
mykitchen/api.py
mykitchen/asgi.py
mykitchen/settings.py
mykitchen/urls.py
mykitchen/wsgi.py
mykitchen/mykitchen_cookbook/__init__.py
mykitchen/mykitchen_cookbook/apps.py
mykitchen/mykitchen_cookbook/kitchen.py
mykitchen/mykitchen_cookbook/migrations/__init__.py
mykitchen-0.0.1.dist-info/METADATA
mykitchen-0.0.1.dist-info/WHEEL
mykitchen-0.0.1.dist-info/licenses/LICENSE
mykitchen-0.0.1.dist-info/RECORD
