Metadata-Version: 2.3
Name: mykitchen
Version: 0.0.1
Author-email: author <author@example.com>
License-File: LICENSE
Classifier: Programming Language :: Python :: 3 :: Only
Classifier: Programming Language :: Python :: 3.11
Classifier: Programming Language :: Python :: 3.12
Requires-Python: >=3.11
Requires-Dist: boto3
Requires-Dist: chromadb
Requires-Dist: diskcache
Requires-Dist: django-allauth[socialaccount]
Requires-Dist: django-compressor
Requires-Dist: django-extensions
Requires-Dist: django-health-check
Requires-Dist: django-lifecycle
Requires-Dist: django-ninja
Requires-Dist: django-q-registry
Requires-Dist: django-q2
Requires-Dist: django-storages[s3]
Requires-Dist: django-template-partials
Requires-Dist: django-unique-user-email
Requires-Dist: django[argon2]
Requires-Dist: djp
Requires-Dist: environs[django]
Requires-Dist: gunicorn
Requires-Dist: kitchenai-sdk==0.1.5a1
Requires-Dist: llama-index
Requires-Dist: llama-index-vector-stores-chroma
Requires-Dist: pillow
Requires-Dist: psycopg[binary]
Requires-Dist: sentry-sdk
Requires-Dist: starlette
Requires-Dist: tomli
Requires-Dist: uvicorn
Requires-Dist: whitenoise
